{"frames": [

{
	"filename": "tunaNet0.png",
	"frame": {"x":2,"y":2,"w":151,"h":148},
	"rotated": false,
	"trimmed": false,
	"spriteSourceSize": {"x":0,"y":0,"w":151,"h":148},
	"sourceSize": {"w":151,"h":148}
},
{
	"filename": "tunaNet1.png",
	"frame": {"x":155,"y":2,"w":151,"h":148},
	"rotated": false,
	"trimmed": false,
	"spriteSourceSize": {"x":0,"y":0,"w":151,"h":148},
	"sourceSize": {"w":151,"h":148}
},
{
	"filename": "tunaNet2.png",
	"frame": {"x":308,"y":2,"w":151,"h":148},
	"rotated": false,
	"trimmed": false,
	"spriteSourceSize": {"x":0,"y":0,"w":151,"h":148},
	"sourceSize": {"w":151,"h":148}
},
{
	"filename": "tunaNet3.png",
	"frame": {"x":2,"y":152,"w":151,"h":148},
	"rotated": false,
	"trimmed": false,
	"spriteSourceSize": {"x":0,"y":0,"w":151,"h":148},
	"sourceSize": {"w":151,"h":148}
},
{
	"filename": "tunaNet4.png",
	"frame": {"x":155,"y":152,"w":151,"h":148},
	"rotated": false,
	"trimmed": false,
	"spriteSourceSize": {"x":0,"y":0,"w":151,"h":148},
	"sourceSize": {"w":151,"h":148}
},
{
	"filename": "tunaNet5.png",
	"frame": {"x":308,"y":152,"w":151,"h":148},
	"rotated": false,
	"trimmed": false,
	"spriteSourceSize": {"x":0,"y":0,"w":151,"h":148},
	"sourceSize": {"w":151,"h":148}
},
{
	"filename": "tunaNet6.png",
	"frame": {"x":2,"y":302,"w":151,"h":148},
	"rotated": false,
	"trimmed": false,
	"spriteSourceSize": {"x":0,"y":0,"w":151,"h":148},
	"sourceSize": {"w":151,"h":148}
},
{
	"filename": "tunaNet7.png",
	"frame": {"x":155,"y":302,"w":151,"h":148},
	"rotated": false,
	"trimmed": false,
	"spriteSourceSize": {"x":0,"y":0,"w":151,"h":148},
	"sourceSize": {"w":151,"h":148}
},
{
	"filename": "tunaNet8.png",
	"frame": {"x":308,"y":302,"w":151,"h":148},
	"rotated": false,
	"trimmed": false,
	"spriteSourceSize": {"x":0,"y":0,"w":151,"h":148},
	"sourceSize": {"w":151,"h":148}
}],
"meta": {
	"app": "http://www.codeandweb.com/texturepacker ",
	"version": "1.0",
	"image": "tunaNet.png",
	"format": "RGBA8888",
	"size": {"w":461,"h":452},
	"scale": "1",
	"smartupdate": "$TexturePacker:SmartUpdate:63c47f013fb3db49b7a7ff0af7626c17:2f57b062ba13cc61c9e4a75bca78afd0:fa7e1d7cc7bce33650d7351ebfdedf28$"
}
}
